pancakeswap_lottery/__init__.py
pancakeswap_lottery/assets/CakeToken.abi
pancakeswap_lottery/assets/LotteryNFT.abi
pancakeswap_lottery/assets/LotteryUpgradeProxy.abi
pancakeswap_lottery/assets/PancakeSwapLottery.abi
pancakeswap_lottery/lottery.py
pancakeswap_lottery/lotteryv2.py
pancakeswap_lottery/utils.py
pancakeswap_lottery-2.1.0.dist-info/LICENSE
pancakeswap_lottery-2.1.0.dist-info/METADATA
pancakeswap_lottery-2.1.0.dist-info/WHEEL
pancakeswap_lottery-2.1.0.dist-info/RECORD
