Metadata-Version: 2.1
Name: pancakeswap-lottery
Version: 2.1.0
Summary: A Python client for accessing PancakeSwap Lottery smart contract information through Web3.py
Home-page: https://github.com/frefrik/pancakeswap-lottery
License: MIT
Keywords: pancakeswap,cake,lottery,bsc,web3
Author: Fredrik Haarstad
Author-email: codemonkey@zomg.no
Requires-Python: >=3.9,<4.0
Classifier: Intended Audience :: Developers
Classifier: Intended Audience :: Financial and Insurance Industry
Classifier: Intended Audience :: Information Technology
Classifier: License :: OSI Approved :: MIT License
Classifier: Programming Language :: Python
Classifier: Programming Language :: Python :: 3
Classifier: Programming Language :: Python :: 3.9
Classifier: Programming Language :: Python :: 3.10
Classifier: Programming Language :: Python :: 3.11
Classifier: Programming Language :: Python :: 3.12
Classifier: Topic :: Software Development :: Libraries :: Python Modules
Requires-Dist: web3 (>=6.18.0,<7.0.0)
Project-URL: Repository, https://github.com/frefrik/pancakeswap-lottery
